Workbook

Sheet 📊 DASHBOARD
B1: ACETRUE TECHNOLOGIES
B2: 📱 Electronics & Accessories — Daily Operations Tracker
B3: =CONCATENATE("Last Refreshed: ",TEXT(NOW(),"DD-MMM-YYYY HH:MM AM/PM")) -> Last Refreshed: 08-Mar-2026 01:33 PM
B4: 💰 TODAY'S REVENUE | D4: 🛒 ITEMS SOLD TODAY | F4: 📦 TOTAL INVENTORY VALUE
B5: =SUMIF('💰 DAILY SALES'!B:B,TODAY(),'💰 DAILY SALES'!G:G) -> 0 | D5: =SUMIF('💰 DAILY SALES'!B:B,TODAY(),'💰 DAILY SALES'!F:F) -> 0 | F5: =SUMPRODUCT('📦 INVENTORY'!G3:G15,'📦 INVENTORY'!I3:I15) -> 303600
B7: ⚠️ LOW STOCK ALERTS
B8: Product | C8: Current Stock | D8: Reorder Level | E8: Units Needed | F8: Status
B9: ='📦 INVENTORY'!B3 -> EarPods | C9: ='📦 INVENTORY'!G3 -> 20 | D9: ='📦 INVENTORY'!H3 -> 5 | E9: =MAX(0,'📦 INVENTORY'!H3-'📦 INVENTORY'!G3) -> 0 | F9: =IF('📦 INVENTORY'!G3<='📦 INVENTORY'!H3,"🔴 REORDER NOW",IF('📦 INVENTORY'!G3<='📦 INVENTORY'!H3*1.5,"🟡 LOW","🟢 OK")) -> 🟢 OK
B10: ='📦 INVENTORY'!B4 -> Button Phone | C10: ='📦 INVENTORY'!G4 -> 10 | D10: ='📦 INVENTORY'!H4 -> 3 | E10: =MAX(0,'📦 INVENTORY'!H4-'📦 INVENTORY'!G4) -> 0 | F10: =IF('📦 INVENTORY'!G4<='📦 INVENTORY'!H4,"🔴 REORDER NOW",IF('📦 INVENTORY'!G4<='📦 INVENTORY'!H4*1.5,"🟡 LOW","🟢 OK")) -> 🟢 OK
B11: ='📦 INVENTORY'!B5 -> Memory Card | C11: ='📦 INVENTORY'!G5 -> 30 | D11: ='📦 INVENTORY'!H5 -> 10 | E11: =MAX(0,'📦 INVENTORY'!H5-'📦 INVENTORY'!G5) -> 0 | F11: =IF('📦 INVENTORY'!G5<='📦 INVENTORY'!H5,"🔴 REORDER NOW",IF('📦 INVENTORY'!G5<='📦 INVENTORY'!H5*1.5,"🟡 LOW","🟢 OK")) -> 🟢 OK
B12: ='📦 INVENTORY'!B6 -> Charger | C12: ='📦 INVENTORY'!G6 -> 25 | D12: ='📦 INVENTORY'!H6 -> 8 | E12: =MAX(0,'📦 INVENTORY'!H6-'📦 INVENTORY'!G6) -> 0 | F12: =IF('📦 INVENTORY'!G6<='📦 INVENTORY'!H6,"🔴 REORDER NOW",IF('📦 INVENTORY'!G6<='📦 INVENTORY'!H6*1.5,"🟡 LOW","🟢 OK")) -> 🟢 OK
B13: ='📦 INVENTORY'!B7 -> Tripod Stand | C13: ='📦 INVENTORY'!G7 -> 8 | D13: ='📦 INVENTORY'!H7 -> 3 | E13: =MAX(0,'📦 INVENTORY'!H7-'📦 INVENTORY'!G7) -> 0 | F13: =IF('📦 INVENTORY'!G7<='📦 INVENTORY'!H7,"🔴 REORDER NOW",IF('📦 INVENTORY'!G7<='📦 INVENTORY'!H7*1.5,"🟡 LOW","🟢 OK")) -> 🟢 OK
B14: ='📦 INVENTORY'!B8 -> Selfie Stick | C14: ='📦 INVENTORY'!G8 -> 10 | D14: ='📦 INVENTORY'!H8 -> 3 | E14: =MAX(0,'📦 INVENTORY'!H8-'📦 INVENTORY'!G8) -> 0 | F14: =IF('📦 INVENTORY'!G8<='📦 INVENTORY'!H8,"🔴 REORDER NOW",IF('📦 INVENTORY'!G8<='📦 INVENTORY'!H8*1.5,"🟡 LOW","🟢 OK")) -> 🟢 OK
B15: ='📦 INVENTORY'!B9 -> Cables | C15: ='📦 INVENTORY'!G9 -> 40 | D15: ='📦 INVENTORY'!H9 -> 15 | E15: =MAX(0,'📦 INVENTORY'!H9-'📦 INVENTORY'!G9) -> 0 | F15: =IF('📦 INVENTORY'!G9<='📦 INVENTORY'!H9,"🔴 REORDER NOW",IF('📦 INVENTORY'!G9<='📦 INVENTORY'!H9*1.5,"🟡 LOW","🟢 OK")) -> 🟢 OK
B16: ='📦 INVENTORY'!B10 -> Ringlight | C16: ='📦 INVENTORY'!G10 -> 5 | D16: ='📦 INVENTORY'!H10 -> 2 | E16: =MAX(0,'📦 INVENTORY'!H10-'📦 INVENTORY'!G10) -> 0 | F16: =IF('📦 INVENTORY'!G10<='📦 INVENTORY'!H10,"🔴 REORDER NOW",IF('📦 INVENTORY'!G10<='📦 INVENTORY'!H10*1.5,"🟡 LOW","🟢 OK")) -> 🟢 OK
B17: ='📦 INVENTORY'!B11 -> Speakers | C17: ='📦 INVENTORY'!G11 -> 8 | D17: ='📦 INVENTORY'!H11 -> 3 | E17: =MAX(0,'📦 INVENTORY'!H11-'📦 INVENTORY'!G11) -> 0 | F17: =IF('📦 INVENTORY'!G11<='📦 INVENTORY'!H11,"🔴 REORDER NOW",IF('📦 INVENTORY'!G11<='📦 INVENTORY'!H11*1.5,"🟡 LOW","🟢 OK")) -> 🟢 OK
B18: ='📦 INVENTORY'!B12 -> Wireless Mic | C18: ='📦 INVENTORY'!G12 -> 6 | D18: ='📦 INVENTORY'!H12 -> 2 | E18: =MAX(0,'📦 INVENTORY'!H12-'📦 INVENTORY'!G12) -> 0 | F18: =IF('📦 INVENTORY'!G12<='📦 INVENTORY'!H12,"🔴 REORDER NOW",IF('📦 INVENTORY'!G12<='📦 INVENTORY'!H12*1.5,"🟡 LOW","🟢 OK")) -> 🟢 OK
B19: ='📦 INVENTORY'!B13 -> Mouse | C19: ='📦 INVENTORY'!G13 -> 12 | D19: ='📦 INVENTORY'!H13 -> 4 | E19: =MAX(0,'📦 INVENTORY'!H13-'📦 INVENTORY'!G13) -> 0 | F19: =IF('📦 INVENTORY'!G13<='📦 INVENTORY'!H13,"🔴 REORDER NOW",IF('📦 INVENTORY'!G13<='📦 INVENTORY'!H13*1.5,"🟡 LOW","🟢 OK")) -> 🟢 OK
B20: ='📦 INVENTORY'!B14 -> Powerbanks | C20: ='📦 INVENTORY'!G14 -> 10 | D20: ='📦 INVENTORY'!H14 -> 3 | E20: =MAX(0,'📦 INVENTORY'!H14-'📦 INVENTORY'!G14) -> 0 | F20: =IF('📦 INVENTORY'!G14<='📦 INVENTORY'!H14,"🔴 REORDER NOW",IF('📦 INVENTORY'!G14<='📦 INVENTORY'!H14*1.5,"🟡 LOW","🟢 OK")) -> 🟢 OK
B21: ='📦 INVENTORY'!B15 -> Smartwatch | C21: ='📦 INVENTORY'!G15 -> 7 | D21: ='📦 INVENTORY'!H15 -> 2 | E21: =MAX(0,'📦 INVENTORY'!H15-'📦 INVENTORY'!G15) -> 0 | F21: =IF('📦 INVENTORY'!G15<='📦 INVENTORY'!H15,"🔴 REORDER NOW",IF('📦 INVENTORY'!G15<='📦 INVENTORY'!H15*1.5,"🟡 LOW","🟢 OK")) -> 🟢 OK
B24: 📅 THIS MONTH'S REVENUE BY PRODUCT
B25: Product | C25: Units Sold | D25: Revenue (₦) | E25: Avg Unit Price
B26: EarPods | C26: =SUMPRODUCT((ISNUMBER('💰 DAILY SALES'!B$2:B$5000))*(MONTH(IF(ISNUMBER('💰 DAILY SALES'!B$2:B$5000),'💰 DAILY SALES'!B$2:B$5000,1))=MONTH(TODAY()))*(YEAR(IF(ISNUMBER('💰 DAILY SALES'!B$2:B$5000),'💰 DAILY SALES'!B$2:B$5000,1))=YEAR(TODAY()))*('💰 DAILY SALES'!D$2:D$5000="EarPods")*IF(ISNUMBER('💰 DAILY SALES'!F$2:F$5000),'💰 DAILY SALES'!F$2:F$5000,0)) -> 0 | D26: =SUMPRODUCT((ISNUMBER('💰 DAILY SALES'!B$2:B$5000))*(MONTH(IF(ISNUMBER('💰 DAILY SALES'!B$2:B$5000),'💰 DAILY SALES'!B$2:B$5000,1))=MONTH(TODAY()))*(YEAR(IF(ISNUMBER('💰 DAILY SALES'!B$2:B$5000),'💰 DAILY SALES'!B$2:B$5000,1))=YEAR(TODAY()))*('💰 DAILY SALES'!D$2:D$5000="EarPods")*IF(ISNUMBER('💰 DAILY SALES'!G$2:G$5000),'💰 DAILY SALES'!G$2:G$5000,0)) -> 0 | E26: =IFERROR(D26/C26,"-") -> -
B27: Button Phone | C27: =SUMPRODUCT((ISNUMBER('💰 DAILY SALES'!B$2:B$5000))*(MONTH(IF(ISNUMBER('💰 DAILY SALES'!B$2:B$5000),'💰 DAILY SALES'!B$2:B$5000,1))=MONTH(TODAY()))*(YEAR(IF(ISNUMBER('💰 DAILY SALES'!B$2:B$5000),'💰 DAILY SALES'!B$2:B$5000,1))=YEAR(TODAY()))*('💰 DAILY SALES'!D$2:D$5000="Button Phone")*IF(ISNUMBER('💰 DAILY SALES'!F$2:F$5000),'💰 DAILY SALES'!F$2:F$5000,0)) -> 0 | D27: =SUMPRODUCT((ISNUMBER('💰 DAILY SALES'!B$2:B$5000))*(MONTH(IF(ISNUMBER('💰 DAILY SALES'!B$2:B$5000),'💰 DAILY SALES'!B$2:B$5000,1))=MONTH(TODAY()))*(YEAR(IF(ISNUMBER('💰 DAILY SALES'!B$2:B$5000),'💰 DAILY SALES'!B$2:B$5000,1))=YEAR(TODAY()))*('💰 DAILY SALES'!D$2:D$5000="Button Phone")*IF(ISNUMBER('💰 DAILY SALES'!G$2:G$5000),'💰 DAILY SALES'!G$2:G$5000,0)) -> 0 | E27: =IFERROR(D27/C27,"-") -> -
B28: Memory Card | C28: =SUMPRODUCT((ISNUMBER('💰 DAILY SALES'!B$2:B$5000))*(MONTH(IF(ISNUMBER('💰 DAILY SALES'!B$2:B$5000),'💰 DAILY SALES'!B$2:B$5000,1))=MONTH(TODAY()))*(YEAR(IF(ISNUMBER('💰 DAILY SALES'!B$2:B$5000),'💰 DAILY SALES'!B$2:B$5000,1))=YEAR(TODAY()))*('💰 DAILY SALES'!D$2:D$5000="Memory Card")*IF(ISNUMBER('💰 DAILY SALES'!F$2:F$5000),'💰 DAILY SALES'!F$2:F$5000,0)) -> 0 | D28: =SUMPRODUCT((ISNUMBER('💰 DAILY SALES'!B$2:B$5000))*(MONTH(IF(ISNUMBER('💰 DAILY SALES'!B$2:B$5000),'💰 DAILY SALES'!B$2:B$5000,1))=MONTH(TODAY()))*(YEAR(IF(ISNUMBER('💰 DAILY SALES'!B$2:B$5000),'💰 DAILY SALES'!B$2:B$5000,1))=YEAR(TODAY()))*('💰 DAILY SALES'!D$2:D$5000="Memory Card")*IF(ISNUMBER('💰 DAILY SALES'!G$2:G$5000),'💰 DAILY SALES'!G$2:G$5000,0)) -> 0 | E28: =IFERROR(D28/C28,"-") -> -
B29: Charger | C29: =SUMPRODUCT((ISNUMBER('💰 DAILY SALES'!B$2:B$5000))*(MONTH(IF(ISNUMBER('💰 DAILY SALES'!B$2:B$5000),'💰 DAILY SALES'!B$2:B$5000,1))=MONTH(TODAY()))*(YEAR(IF(ISNUMBER('💰 DAILY SALES'!B$2:B$5000),'💰 DAILY SALES'!B$2:B$5000,1))=YEAR(TODAY()))*('💰 DAILY SALES'!D$2:D$5000="Charger")*IF(ISNUMBER('💰 DAILY SALES'!F$2:F$5000),'💰 DAILY SALES'!F$2:F$5000,0)) -> 0 | D29: =SUMPRODUCT((ISNUMBER('💰 DAILY SALES'!B$2:B$5000))*(MONTH(IF(ISNUMBER('💰 DAILY SALES'!B$2:B$5000),'💰 DAILY SALES'!B$2:B$5000,1))=MONTH(TODAY()))*(YEAR(IF(ISNUMBER('💰 DAILY SALES'!B$2:B$5000),'💰 DAILY SALES'!B$2:B$5000,1))=YEAR(TODAY()))*('💰 DAILY SALES'!D$2:D$5000="Charger")*IF(ISNUMBER('💰 DAILY SALES'!G$2:G$5000),'💰 DAILY SALES'!G$2:G$5000,0)) -> 0 | E29: =IFERROR(D29/C29,"-") -> -
B30: Tripod Stand | C30: =SUMPRODUCT((ISNUMBER('💰 DAILY SALES'!B$2:B$5000))*(MONTH(IF(ISNUMBER('💰 DAILY SALES'!B$2:B$5000),'💰 DAILY SALES'!B$2:B$5000,1))=MONTH(TODAY()))*(YEAR(IF(ISNUMBER('💰 DAILY SALES'!B$2:B$5000),'💰 DAILY SALES'!B$2:B$5000,1))=YEAR(TODAY()))*('💰 DAILY SALES'!D$2:D$5000="Tripod Stand")*IF(ISNUMBER('💰 DAILY SALES'!F$2:F$5000),'💰 DAILY SALES'!F$2:F$5000,0)) -> 0 | D30: =SUMPRODUCT((ISNUMBER('💰 DAILY SALES'!B$2:B$5000))*(MONTH(IF(ISNUMBER('💰 DAILY SALES'!B$2:B$5000),'💰 DAILY SALES'!B$2:B$5000,1))=MONTH(TODAY()))*(YEAR(IF(ISNUMBER('💰 DAILY SALES'!B$2:B$5000),'💰 DAILY SALES'!B$2:B$5000,1))=YEAR(TODAY()))*('💰 DAILY SALES'!D$2:D$5000="Tripod Stand")*IF(ISNUMBER('💰 DAILY SALES'!G$2:G$5000),'💰 DAILY SALES'!G$2:G$5000,0)) -> 0 | E30: =IFERROR(D30/C30,"-") -> -
B31: Selfie Stick | C31: =SUMPRODUCT((ISNUMBER('💰 DAILY SALES'!B$2:B$5000))*(MONTH(IF(ISNUMBER('💰 DAILY SALES'!B$2:B$5000),'💰 DAILY SALES'!B$2:B$5000,1))=MONTH(TODAY()))*(YEAR(IF(ISNUMBER('💰 DAILY SALES'!B$2:B$5000),'💰 DAILY SALES'!B$2:B$5000,1))=YEAR(TODAY()))*('💰 DAILY SALES'!D$2:D$5000="Selfie Stick")*IF(ISNUMBER('💰 DAILY SALES'!F$2:F$5000),'💰 DAILY SALES'!F$2:F$5000,0)) -> 0 | D31: =SUMPRODUCT((ISNUMBER('💰 DAILY SALES'!B$2:B$5000))*(MONTH(IF(ISNUMBER('💰 DAILY SALES'!B$2:B$5000),'💰 DAILY SALES'!B$2:B$5000,1))=MONTH(TODAY()))*(YEAR(IF(ISNUMBER('💰 DAILY SALES'!B$2:B$5000),'💰 DAILY SALES'!B$2:B$5000,1))=YEAR(TODAY()))*('💰 DAILY SALES'!D$2:D$5000="Selfie Stick")*IF(ISNUMBER('💰 DAILY SALES'!G$2:G$5000),'💰 DAILY SALES'!G$2:G$5000,0)) -> 0 | E31: =IFERROR(D31/C31,"-") -> -
B32: Cables | C32: =SUMPRODUCT((ISNUMBER('💰 DAILY SALES'!B$2:B$5000))*(MONTH(IF(ISNUMBER('💰 DAILY SALES'!B$2:B$5000),'💰 DAILY SALES'!B$2:B$5000,1))=MONTH(TODAY()))*(YEAR(IF(ISNUMBER('💰 DAILY SALES'!B$2:B$5000),'💰 DAILY SALES'!B$2:B$5000,1))=YEAR(TODAY()))*('💰 DAILY SALES'!D$2:D$5000="Cables")*IF(ISNUMBER('💰 DAILY SALES'!F$2:F$5000),'💰 DAILY SALES'!F$2:F$5000,0)) -> 0 | D32: =SUMPRODUCT((ISNUMBER('💰 DAILY SALES'!B$2:B$5000))*(MONTH(IF(ISNUMBER('💰 DAILY SALES'!B$2:B$5000),'💰 DAILY SALES'!B$2:B$5000,1))=MONTH(TODAY()))*(YEAR(IF(ISNUMBER('💰 DAILY SALES'!B$2:B$5000),'💰 DAILY SALES'!B$2:B$5000,1))=YEAR(TODAY()))*('💰 DAILY SALES'!D$2:D$5000="Cables")*IF(ISNUMBER('💰 DAILY SALES'!G$2:G$5000),'💰 DAILY SALES'!G$2:G$5000,0)) -> 0 | E32: =IFERROR(D32/C32,"-") -> -
B33: Ringlight | C33: =SUMPRODUCT((ISNUMBER('💰 DAILY SALES'!B$2:B$5000))*(MONTH(IF(ISNUMBER('💰 DAILY SALES'!B$2:B$5000),'💰 DAILY SALES'!B$2:B$5000,1))=MONTH(TODAY()))*(YEAR(IF(ISNUMBER('💰 DAILY SALES'!B$2:B$5000),'💰 DAILY SALES'!B$2:B$5000,1))=YEAR(TODAY()))*('💰 DAILY SALES'!D$2:D$5000="Ringlight")*IF(ISNUMBER('💰 DAILY SALES'!F$2:F$5000),'💰 DAILY SALES'!F$2:F$5000,0)) -> 0 | D33: =SUMPRODUCT((ISNUMBER('💰 DAILY SALES'!B$2:B$5000))*(MONTH(IF(ISNUMBER('💰 DAILY SALES'!B$2:B$5000),'💰 DAILY SALES'!B$2:B$5000,1))=MONTH(TODAY()))*(YEAR(IF(ISNUMBER('💰 DAILY SALES'!B$2:B$5000),'💰 DAILY SALES'!B$2:B$5000,1))=YEAR(TODAY()))*('💰 DAILY SALES'!D$2:D$5000="Ringlight")*IF(ISNUMBER('💰 DAILY SALES'!G$2:G$5000),'💰 DAILY SALES'!G$2:G$5000,0)) -> 0 | E33: =IFERROR(D33/C33,"-") -> -
B34: Speakers | C34: =SUMPRODUCT((ISNUMBER('💰 DAILY SALES'!B$2:B$5000))*(MONTH(IF(ISNUMBER('💰 DAILY SALES'!B$2:B$5000),'💰 DAILY SALES'!B$2:B$5000,1))=MONTH(TODAY()))*(YEAR(IF(ISNUMBER('💰 DAILY SALES'!B$2:B$5000),'💰 DAILY SALES'!B$2:B$5000,1))=YEAR(TODAY()))*('💰 DAILY SALES'!D$2:D$5000="Speakers")*IF(ISNUMBER('💰 DAILY SALES'!F$2:F$5000),'💰 DAILY SALES'!F$2:F$5000,0)) -> 0 | D34: =SUMPRODUCT((ISNUMBER('💰 DAILY SALES'!B$2:B$5000))*(MONTH(IF(ISNUMBER('💰 DAILY SALES'!B$2:B$5000),'💰 DAILY SALES'!B$2:B$5000,1))=MONTH(TODAY()))*(YEAR(IF(ISNUMBER('💰 DAILY SALES'!B$2:B$5000),'💰 DAILY SALES'!B$2:B$5000,1))=YEAR(TODAY()))*('💰 DAILY SALES'!D$2:D$5000="Speakers")*IF(ISNUMBER('💰 DAILY SALES'!G$2:G$5000),'💰 DAILY SALES'!G$2:G$5000,0)) -> 0 | E34: =IFERROR(D34/C34,"-") -> -
B35: Wireless Mic | C35: =SUMPRODUCT((ISNUMBER('💰 DAILY SALES'!B$2:B$5000))*(MONTH(IF(ISNUMBER('💰 DAILY SALES'!B$2:B$5000),'💰 DAILY SALES'!B$2:B$5000,1))=MONTH(TODAY()))*(YEAR(IF(ISNUMBER('💰 DAILY SALES'!B$2:B$5000),'💰 DAILY SALES'!B$2:B$5000,1))=YEAR(TODAY()))*('💰 DAILY SALES'!D$2:D$5000="Wireless Mic")*IF(ISNUMBER('💰 DAILY SALES'!F$2:F$5000),'💰 DAILY SALES'!F$2:F$5000,0)) -> 0 | D35: =SUMPRODUCT((ISNUMBER('💰 DAILY SALES'!B$2:B$5000))*(MONTH(IF(ISNUMBER('💰 DAILY SALES'!B$2:B$5000),'💰 DAILY SALES'!B$2:B$5000,1))=MONTH(TODAY()))*(YEAR(IF(ISNUMBER('💰 DAILY SALES'!B$2:B$5000),'💰 DAILY SALES'!B$2:B$5000,1))=YEAR(TODAY()))*('💰 DAILY SALES'!D$2:D$5000="Wireless Mic")*IF(ISNUMBER('💰 DAILY SALES'!G$2:G$5000),'💰 DAILY SALES'!G$2:G$5000,0)) -> 0 | E35: =IFERROR(D35/C35,"-") -> -
B36: Mouse | C36: =SUMPRODUCT((ISNUMBER('💰 DAILY SALES'!B$2:B$5000))*(MONTH(IF(ISNUMBER('💰 DAILY SALES'!B$2:B$5000),'💰 DAILY SALES'!B$2:B$5000,1))=MONTH(TODAY()))*(YEAR(IF(ISNUMBER('💰 DAILY SALES'!B$2:B$5000),'💰 DAILY SALES'!B$2:B$5000,1))=YEAR(TODAY()))*('💰 DAILY SALES'!D$2:D$5000="Mouse")*IF(ISNUMBER('💰 DAILY SALES'!F$2:F$5000),'💰 DAILY SALES'!F$2:F$5000,0)) -> 0 | D36: =SUMPRODUCT((ISNUMBER('💰 DAILY SALES'!B$2:B$5000))*(MONTH(IF(ISNUMBER('💰 DAILY SALES'!B$2:B$5000),'💰 DAILY SALES'!B$2:B$5000,1))=MONTH(TODAY()))*(YEAR(IF(ISNUMBER('💰 DAILY SALES'!B$2:B$5000),'💰 DAILY SALES'!B$2:B$5000,1))=YEAR(TODAY()))*('💰 DAILY SALES'!D$2:D$5000="Mouse")*IF(ISNUMBER('💰 DAILY SALES'!G$2:G$5000),'💰 DAILY SALES'!G$2:G$5000,0)) -> 0 | E36: =IFERROR(D36/C36,"-") -> -
B37: Powerbanks | C37: =SUMPRODUCT((ISNUMBER('💰 DAILY SALES'!B$2:B$5000))*(MONTH(IF(ISNUMBER('💰 DAILY SALES'!B$2:B$5000),'💰 DAILY SALES'!B$2:B$5000,1))=MONTH(TODAY()))*(YEAR(IF(ISNUMBER('💰 DAILY SALES'!B$2:B$5000),'💰 DAILY SALES'!B$2:B$5000,1))=YEAR(TODAY()))*('💰 DAILY SALES'!D$2:D$5000="Powerbanks")*IF(ISNUMBER('💰 DAILY SALES'!F$2:F$5000),'💰 DAILY SALES'!F$2:F$5000,0)) -> 0 | D37: =SUMPRODUCT((ISNUMBER('💰 DAILY SALES'!B$2:B$5000))*(MONTH(IF(ISNUMBER('💰 DAILY SALES'!B$2:B$5000),'💰 DAILY SALES'!B$2:B$5000,1))=MONTH(TODAY()))*(YEAR(IF(ISNUMBER('💰 DAILY SALES'!B$2:B$5000),'💰 DAILY SALES'!B$2:B$5000,1))=YEAR(TODAY()))*('💰 DAILY SALES'!D$2:D$5000="Powerbanks")*IF(ISNUMBER('💰 DAILY SALES'!G$2:G$5000),'💰 DAILY SALES'!G$2:G$5000,0)) -> 0 | E37: =IFERROR(D37/C37,"-") -> -
B38: Smartwatch | C38: =SUMPRODUCT((ISNUMBER('💰 DAILY SALES'!B$2:B$5000))*(MONTH(IF(ISNUMBER('💰 DAILY SALES'!B$2:B$5000),'💰 DAILY SALES'!B$2:B$5000,1))=MONTH(TODAY()))*(YEAR(IF(ISNUMBER('💰 DAILY SALES'!B$2:B$5000),'💰 DAILY SALES'!B$2:B$5000,1))=YEAR(TODAY()))*('💰 DAILY SALES'!D$2:D$5000="Smartwatch")*IF(ISNUMBER('💰 DAILY SALES'!F$2:F$5000),'💰 DAILY SALES'!F$2:F$5000,0)) -> 0 | D38: =SUMPRODUCT((ISNUMBER('💰 DAILY SALES'!B$2:B$5000))*(MONTH(IF(ISNUMBER('💰 DAILY SALES'!B$2:B$5000),'💰 DAILY SALES'!B$2:B$5000,1))=MONTH(TODAY()))*(YEAR(IF(ISNUMBER('💰 DAILY SALES'!B$2:B$5000),'💰 DAILY SALES'!B$2:B$5000,1))=YEAR(TODAY()))*('💰 DAILY SALES'!D$2:D$5000="Smartwatch")*IF(ISNUMBER('💰 DAILY SALES'!G$2:G$5000),'💰 DAILY SALES'!G$2:G$5000,0)) -> 0 | E38: =IFERROR(D38/C38,"-") -> -
B39: TOTAL | C39: =SUM(C26:C38) -> 0 | D39: =SUM(D26:D38) -> 0

Sheet 📦 INVENTORY
B1: 📦 INVENTORY MANAGEMENT — ACETRUE TECHNOLOGIES
B2: Product | C2: Opening Stock | D2: Stock In (Purchased) | E2: Stock Sold (All Time) | F2: 💀 Damaged / Adjust | G2: Current Stock | H2: Reorder Level | I2: Cost Price (₦) | J2: Selling Price (₦) | K2: Stock Value (₦)
B3: EarPods | C3: 20 | D3: =SUMIF('📥 STOCK IN'!C:C,B3,'📥 STOCK IN'!D:D) -> 0 | E3: =SUMIF('💰 DAILY SALES'!D:D,B3,'💰 DAILY SALES'!F:F) -> 0 | F3: 0 | G3: =C3+D3-E3-F3 -> 20 | H3: 5 | I3: 800 | J3: 1500 | K3: =G3*I3 -> 16000
B4: Button Phone | C4: 10 | D4: =SUMIF('📥 STOCK IN'!C:C,B4,'📥 STOCK IN'!D:D) -> 0 | E4: =SUMIF('💰 DAILY SALES'!D:D,B4,'💰 DAILY SALES'!F:F) -> 0 | F4: 0 | G4: =C4+D4-E4-F4 -> 10 | H4: 3 | I4: 3500 | J4: 6000 | K4: =G4*I4 -> 35000
B5: Memory Card | C5: 30 | D5: =SUMIF('📥 STOCK IN'!C:C,B5,'📥 STOCK IN'!D:D) -> 0 | E5: =SUMIF('💰 DAILY SALES'!D:D,B5,'💰 DAILY SALES'!F:F) -> 0 | F5: 0 | G5: =C5+D5-E5-F5 -> 30 | H5: 10 | I5: 500 | J5: 1000 | K5: =G5*I5 -> 15000
B6: Charger | C6: 25 | D6: =SUMIF('📥 STOCK IN'!C:C,B6,'📥 STOCK IN'!D:D) -> 0 | E6: =SUMIF('💰 DAILY SALES'!D:D,B6,'💰 DAILY SALES'!F:F) -> 0 | F6: 0 | G6: =C6+D6-E6-F6 -> 25 | H6: 8 | I6: 600 | J6: 1200 | K6: =G6*I6 -> 15000
B7: Tripod Stand | C7: 8 | D7: =SUMIF('📥 STOCK IN'!C:C,B7,'📥 STOCK IN'!D:D) -> 0 | E7: =SUMIF('💰 DAILY SALES'!D:D,B7,'💰 DAILY SALES'!F:F) -> 0 | F7: 0 | G7: =C7+D7-E7-F7 -> 8 | H7: 3 | I7: 2500 | J7: 4500 | K7: =G7*I7 -> 20000
B8: Selfie Stick | C8: 10 | D8: =SUMIF('📥 STOCK IN'!C:C,B8,'📥 STOCK IN'!D:D) -> 0 | E8: =SUMIF('💰 DAILY SALES'!D:D,B8,'💰 DAILY SALES'!F:F) -> 0 | F8: 0 | G8: =C8+D8-E8-F8 -> 10 | H8: 3 | I8: 1500 | J8: 2500 | K8: =G8*I8 -> 15000
B9: Cables | C9: 40 | D9: =SUMIF('📥 STOCK IN'!C:C,B9,'📥 STOCK IN'!D:D) -> 0 | E9: =SUMIF('💰 DAILY SALES'!D:D,B9,'💰 DAILY SALES'!F:F) -> 0 | F9: 0 | G9: =C9+D9-E9-F9 -> 40 | H9: 15 | I9: 400 | J9: 800 | K9: =G9*I9 -> 16000
B10: Ringlight | C10: 5 | D10: =SUMIF('📥 STOCK IN'!C:C,B10,'📥 STOCK IN'!D:D) -> 0 | E10: =SUMIF('💰 DAILY SALES'!D:D,B10,'💰 DAILY SALES'!F:F) -> 0 | F10: 0 | G10: =C10+D10-E10-F10 -> 5 | H10: 2 | I10: 5000 | J10: 8500 | K10: =G10*I10 -> 25000
B11: Speakers | C11: 8 | D11: =SUMIF('📥 STOCK IN'!C:C,B11,'📥 STOCK IN'!D:D) -> 0 | E11: =SUMIF('💰 DAILY SALES'!D:D,B11,'💰 DAILY SALES'!F:F) -> 0 | F11: 0 | G11: =C11+D11-E11-F11 -> 8 | H11: 3 | I11: 3000 | J11: 5500 | K11: =G11*I11 -> 24000
B12: Wireless Mic | C12: 6 | D12: =SUMIF('📥 STOCK IN'!C:C,B12,'📥 STOCK IN'!D:D) -> 0 | E12: =SUMIF('💰 DAILY SALES'!D:D,B12,'💰 DAILY SALES'!F:F) -> 0 | F12: 0 | G12: =C12+D12-E12-F12 -> 6 | H12: 2 | I12: 4000 | J12: 7000 | K12: =G12*I12 -> 24000
B13: Mouse | C13: 12 | D13: =SUMIF('📥 STOCK IN'!C:C,B13,'📥 STOCK IN'!D:D) -> 0 | E13: =SUMIF('💰 DAILY SALES'!D:D,B13,'💰 DAILY SALES'!F:F) -> 0 | F13: 0 | G13: =C13+D13-E13-F13 -> 12 | H13: 4 | I13: 1800 | J13: 3200 | K13: =G13*I13 -> 21600
B14: Powerbanks | C14: 10 | D14: =SUMIF('📥 STOCK IN'!C:C,B14,'📥 STOCK IN'!D:D) -> 0 | E14: =SUMIF('💰 DAILY SALES'!D:D,B14,'💰 DAILY SALES'!F:F) -> 0 | F14: 0 | G14: =C14+D14-E14-F14 -> 10 | H14: 3 | I14: 3500 | J14: 6000 | K14: =G14*I14 -> 35000
B15: Smartwatch | C15: 7 | D15: =SUMIF('📥 STOCK IN'!C:C,B15,'📥 STOCK IN'!D:D) -> 0 | E15: =SUMIF('💰 DAILY SALES'!D:D,B15,'💰 DAILY SALES'!F:F) -> 0 | F15: 0 | G15: =C15+D15-E15-F15 -> 7 | H15: 2 | I15: 6000 | J15: 10000 | K15: =G15*I15 -> 42000
B16: TOTAL / SUMMARY | C16: =SUM(C3:C15) -> 191 | D16: =SUM(D3:D15) -> 0 | E16: =SUM(E3:E15) -> 0 | F16: =SUM(F3:F15) -> 0 | G16: =SUM(G3:G15) -> 191 | K16: =SUM(K3:K15) -> 303600
B18: 📘 HOW TO USE THIS SHEET
B19: 🔵 Blue text cells = INPUT CELLS — you can edit these directly (Opening Stock, Reorder Level, Cost & Selling Prices).
B20: ⚙️ 'Stock In' auto-calculates from the 📥 STOCK IN sheet. 'Stock Sold' auto-calculates from 💰 DAILY SALES.
B21: 💀 'Damaged/Adjust' column: Enter positive numbers for damaged/lost/returned items that reduce stock.
B22: 🔴 Red rows = Below reorder level (URGENT: Restock!). 🟡 Yellow = Low (approaching reorder). 🟢 = OK.
B23: 📌 IMPORTANT: Change Opening Stock only ONCE when you first set up. After that, all changes go through STOCK IN or DAILY SALES.

Sheet 💰 DAILY SALES
B1: 💰 DAILY SALES LOG — ACETRUE TECHNOLOGIES
B2: Date | C2: Day | D2: Product | E2: Variant / Note | F2: Qty Sold | G2: Unit Price (₦) | H2: Total (₦) | I2: Payment Method | J2: Recorded By
C3: =IF(B3="","",TEXT(B3,"DDD")) | G3: =IF(D3="","",IFERROR(VLOOKUP(D3,'📦 INVENTORY'!B:J,9,0),"")) | H3: =IF(OR(F3="",G3=""),"",F3*G3)
C4: =IF(B4="","",TEXT(B4,"DDD")) | G4: =IF(D4="","",IFERROR(VLOOKUP(D4,'📦 INVENTORY'!B:J,9,0),"")) | H4: =IF(OR(F4="",G4=""),"",F4*G4)
C5: =IF(B5="","",TEXT(B5,"DDD")) | G5: =IF(D5="","",IFERROR(VLOOKUP(D5,'📦 INVENTORY'!B:J,9,0),"")) | H5: =IF(OR(F5="",G5=""),"",F5*G5)
C6: =IF(B6="","",TEXT(B6,"DDD")) | G6: =IF(D6="","",IFERROR(VLOOKUP(D6,'📦 INVENTORY'!B:J,9,0),"")) | H6: =IF(OR(F6="",G6=""),"",F6*G6)
C7: =IF(B7="","",TEXT(B7,"DDD")) | G7: =IF(D7="","",IFERROR(VLOOKUP(D7,'📦 INVENTORY'!B:J,9,0),"")) | H7: =IF(OR(F7="",G7=""),"",F7*G7)
C8: =IF(B8="","",TEXT(B8,"DDD")) | G8: =IF(D8="","",IFERROR(VLOOKUP(D8,'📦 INVENTORY'!B:J,9,0),"")) | H8: =IF(OR(F8="",G8=""),"",F8*G8)
C9: =IF(B9="","",TEXT(B9,"DDD")) | G9: =IF(D9="","",IFERROR(VLOOKUP(D9,'📦 INVENTORY'!B:J,9,0),"")) | H9: =IF(OR(F9="",G9=""),"",F9*G9)
C10: =IF(B10="","",TEXT(B10,"DDD")) | G10: =IF(D10="","",IFERROR(VLOOKUP(D10,'📦 INVENTORY'!B:J,9,0),"")) | H10: =IF(OR(F10="",G10=""),"",F10*G10)
C11: =IF(B11="","",TEXT(B11,"DDD")) | G11: =IF(D11="","",IFERROR(VLOOKUP(D11,'📦 INVENTORY'!B:J,9,0),"")) | H11: =IF(OR(F11="",G11=""),"",F11*G11)
C12: =IF(B12="","",TEXT(B12,"DDD")) | G12: =IF(D12="","",IFERROR(VLOOKUP(D12,'📦 INVENTORY'!B:J,9,0),"")) | H12: =IF(OR(F12="",G12=""),"",F12*G12)
C13: =IF(B13="","",TEXT(B13,"DDD")) | G13: =IF(D13="","",IFERROR(VLOOKUP(D13,'📦 INVENTORY'!B:J,9,0),"")) | H13: =IF(OR(F13="",G13=""),"",F13*G13)
C14: =IF(B14="","",TEXT(B14,"DDD")) | G14: =IF(D14="","",IFERROR(VLOOKUP(D14,'📦 INVENTORY'!B:J,9,0),"")) | H14: =IF(OR(F14="",G14=""),"",F14*G14)
... C502: =IF(B502="","",TEXT(B502,"DDD")) | G502: =IF(D502="","",IFERROR(VLOOKUP(D502,'📦 INVENTORY'!B:J,9,0),"")) | H502: =IF(OR(F502="",G502=""),"",F502*G502)
B504: 📊 TOTALS SUMMARY
B505: Total Revenue (All Time) | G505: =SUM(H3:H502) -> 0
B506: Total Units Sold (All Time) | G506: =SUM(F3:F502) -> 0
B507: Revenue Today | G507: =SUMIF(B3:B502,TODAY(),H3:H502) -> 0
B508: Revenue This Month | G508: =SUMPRODUCT((MONTH(B3:B502)=MONTH(TODAY()))*(YEAR(B3:B502)=YEAR(TODAY())),IF(ISNUMBER(H3:H502),H3:H502,0)) -> 0
B509: Cash Sales Today | G509: =SUMPRODUCT((B3:B502=TODAY())*(I3:I502="Cash"),IF(ISNUMBER(H3:H502),H3:H502,0)) -> 0
B510: POS Sales Today | G510: =SUMPRODUCT((B3:B502=TODAY())*(I3:I502="POS"),IF(ISNUMBER(H3:H502),H3:H502,0)) -> 0
B511: Transfer Sales Today | G511: =SUMPRODUCT((B3:B502=TODAY())*(I3:I502="Transfer"),IF(ISNUMBER(H3:H502),H3:H502,0)) -> 0

Sheet 📥 STOCK IN
B1: 📥 STOCK IN — PURCHASE & RESTOCK LOG
B2: Date | C2: Product | D2: Qty Received | E2: Unit Cost (₦) | F2: Total Cost (₦) | G2: Supplier Name | H2: Invoice/Receipt No. | I2: Notes
F3: =IF(OR(D3="",E3=""),"",D3*E3)
F4: =IF(OR(D4="",E4=""),"",D4*E4)
F5: =IF(OR(D5="",E5=""),"",D5*E5)
F6: =IF(OR(D6="",E6=""),"",D6*E6)
F7: =IF(OR(D7="",E7=""),"",D7*E7)
F8: =IF(OR(D8="",E8=""),"",D8*E8)
F9: =IF(OR(D9="",E9=""),"",D9*E9)
F10: =IF(OR(D10="",E10=""),"",D10*E10)
F11: =IF(OR(D11="",E11=""),"",D11*E11)
F12: =IF(OR(D12="",E12=""),"",D12*E12)
F13: =IF(OR(D13="",E13=""),"",D13*E13)
F14: =IF(OR(D14="",E14=""),"",D14*E14)
... F502: =IF(OR(D502="",E502=""),"",D502*E502)
B504: TOTAL PURCHASE COST (All Time) | F504: =SUM(F3:F502) -> 0

Sheet 💸 EXPENSES
B1: 💸 BUSINESS EXPENSES LOG
B2: Date | C2: Description | D2: Category | E2: Amount (₦) | F2: Payment Method | G2: Notes
B504: TOTAL EXPENSES (All Time) | E504: =SUM(E3:E502) -> 0

Sheet 📈 PROFIT & LOSS
B1: 📈 PROFIT & LOSS — ACETRUE TECHNOLOGIES
B2: Auto-calculated from Sales, Stock In, and Expenses sheets
B3: INCOME
B4: Total Sales Revenue | C4: =SUM('💰 DAILY SALES'!H3:H502) -> 0
B6: COST OF GOODS SOLD (COGS)
B7: Total Stock Purchased | C7: =SUM('📥 STOCK IN'!F3:F502) -> 0
B9: GROSS PROFIT | C9: =C4-C8 -> 0
B10: Gross Margin % | C10: =IFERROR(C10/C4,0) -> 0
B12: OPERATING EXPENSES
B13: Total Expenses | C13: =SUM('💸 EXPENSES'!E3:E502) -> 0
B15: NET PROFIT | C15: =C10-C14 -> 0
B16: Net Margin % | C16: =IFERROR(C16/C4,0) -> 0

Sheet 📋 HOW TO USE
B1: 📋 HOW TO USE — ACETRUE TECHNOLOGIES TRACKER
B2: SHEET | C2: WHAT IT DOES & HOW TO USE IT
B3: 📊 DASHBOARD | C3: Your command centre. Open this every morning to see your current stock status, today's revenue, and which products need restocking. You don't type anything here — it auto-updates.
B4: 📦 INVENTORY | C4: The master stock list. FIRST TIME SETUP: Enter the correct Opening Stock (column C), Cost Price (column I), Selling Price (column J), and Reorder Level (column H) for each product. After setup, this sheet auto-updates itself from sales and stock-in entries.
B5: 💰 DAILY SALES | C5: Your sales girl uses this EVERY TIME she makes a sale. Steps: (1) Enter today's Date in column B. (2) Click column D and choose the Product from the dropdown. (3) Enter the Quantity sold in column F. The Unit Price auto-fills! (4) Column H (Total) calculates automatically. (5) Choose Payment Method (Cash/POS/Transfer). (6) Enter her name in 'Recorded By'.
B6: 📥 STOCK IN | C6: Use this sheet whenever you receive new stock from your supplier. Enter: Date, Product (dropdown), Qty Received, Unit Cost per item. The Total Cost calculates automatically. Also enter the Supplier name and invoice number for record-keeping.
B7: 💸 EXPENSES | C7: Log ALL business expenses here daily. This includes: rent, transport to get stock, data subscriptions, salaries, bank charges, packaging, etc. Choose a Category from the dropdown.
B8: 📈 PROFIT & LOSS | C8: Automatically shows your total revenue, cost of goods, expenses, gross profit, net profit, and margins. Check this weekly or monthly to understand how your business is performing.
B10: DAILY ROUTINE | C10: RECOMMENDED DAILY WORKFLOW
B11: Morning | C11: 1. Open 📊 DASHBOARD — check stock levels and reorder alerts.
B12: During the day | C12: 2. Sales girl logs every sale in 💰 DAILY SALES as it happens.
B13: When stock arrives | C13: 3. Log new stock in 📥 STOCK IN immediately.
B14: End of day | C14: 4. Log any business expenses in 💸 EXPENSES.
... B22: New Products | C22: To add a new product, add a new row in 📦 INVENTORY and update the product dropdown list in the Data Validation settings.
